termtris/__init__.py
termtris/backend.py
termtris/panel.py
termtris/termtris.py
termtris/tetro.py
termtris-0.10.4.dist-info/METADATA
termtris-0.10.4.dist-info/WHEEL
termtris-0.10.4.dist-info/entry_points.txt
termtris-0.10.4.dist-info/licenses/LICENSE
termtris-0.10.4.dist-info/RECORD
