Metadata-Version: 2.1
Name: termtris
Version: 0.10.4
Summary: A Tetris game in character terminal environment
Project-URL: Homepage, https://github.com/brookssu/termtris
Author-email: Brooks Su <yipeng00@gmail.com>
License:                                  Apache License
License-File: LICENSE
Keywords: game,ltermio,terminal,termtetris,termtris,tetris
Classifier: Development Status :: 4 - Beta
Classifier: Environment :: Console
Classifier: Intended Audience :: End Users/Desktop
Classifier: License :: OSI Approved :: Apache Software License
Classifier: Natural Language :: English
Classifier: Operating System :: MacOS :: MacOS X
Classifier: Operating System :: POSIX
Classifier: Operating System :: Unix
Classifier: Programming Language :: Python :: 3.9
Classifier: Programming Language :: Python :: 3.10
Classifier: Programming Language :: Python :: 3.11
Classifier: Topic :: Games/Entertainment
Requires-Python: >=3.7
Requires-Dist: ltermio>=0.6.2
